sphinxcontrib_napoleon2-1.0-py3.5-nspkg.pth
sphinxcontrib/napoleon/__init__.py
sphinxcontrib/napoleon/_version.py
sphinxcontrib/napoleon/directives.py
sphinxcontrib/napoleon/docstring.py
sphinxcontrib_napoleon2-1.0.dist-info/DESCRIPTION.rst
sphinxcontrib_napoleon2-1.0.dist-info/METADATA
sphinxcontrib_napoleon2-1.0.dist-info/RECORD
sphinxcontrib_napoleon2-1.0.dist-info/WHEEL
sphinxcontrib_napoleon2-1.0.dist-info/metadata.json
sphinxcontrib_napoleon2-1.0.dist-info/namespace_packages.txt
sphinxcontrib_napoleon2-1.0.dist-info/top_level.txt
tests/__init__.py
tests/napoleon/__init__.py
tests/napoleon/test_docstring.py
tests/napoleon/test_napoleon.py
