Metadata-Version: 2.0
Name: sphinxcontrib-napoleon2
Version: 1.0
Summary: Modified Sphinx "napoleon" extension.
Home-page: https://sphinxcontrib-napoleon.readthedocs.io
Author: UNKNOWN
Author-email: UNKNOWN
License: BSD
Download-URL: http://github.com/LinxiFan/sphinxcontrib-napoleon
Platform: any
Classifier: Development Status :: 5 - Production/Stable
Classifier: Environment :: Console
Classifier: Environment :: Web Environment
Classifier: Intended Audience :: Developers
Classifier: License :: OSI Approved :: BSD License
Classifier: Operating System :: OS Independent
Classifier: Programming Language :: Python
Classifier: Programming Language :: Python :: 2
Classifier: Programming Language :: Python :: 3
Classifier: Topic :: Documentation
Classifier: Topic :: Utilities
Classifier: Framework :: Sphinx
Classifier: Framework :: Sphinx :: Extension
Requires-Dist: pockets (>=0.3)
Requires-Dist: six (>=1.5.2)
